{
  "setting": {},
  "condition": {
    "plugin": {
      "list": []
    },
    "game": {
      "list": []
    },
    "gamePlugin": {
      "list": []
    },
    "miniprogram": {
      "list": [
        {
          "name": "test space",
          "pathName": "pages/test/test",
          "query": "",
          "scene": null
        },
        {
          "name": "pages/index/index",
          "pathName": "pages/index/index",
          "query": "",
          "scene": null,
          "partialCompile": {
            "enabled": false,
            "pages": [
              "pages/test/test"
            ]
          }
        },
        {
          "name": "pages/space_show/space_show",
          "pathName": "pages/space_show/space_show",
          "query": "",
          "scene": null
        }
      ]
    }
  }
}